state_handler/__init__.py
state_handler/state.py
state_handler/state_handler.py
ptb_state_handler-0.2.0.dist-info/LICENSE
ptb_state_handler-0.2.0.dist-info/METADATA
ptb_state_handler-0.2.0.dist-info/WHEEL
ptb_state_handler-0.2.0.dist-info/RECORD
